pandashifu/__init__.py
pandashifu/scroll/app.py
pandashifu/scroll/launch.py
pandashifu/studio/app.py
pandashifu/studio/autosource.py
pandashifu/studio/canvas.py
pandashifu/studio/launch.py
pandashifu/studio/requirements.txt
pandashifu/studio/styles.py
pandashifu/studio/toolset.py
pandashifu/studio/components/__init__.py
pandashifu/studio/components/color_input.py
pandashifu/studio/images/acf_and_pacf.png
pandashifu/studio/images/add_columns.png
pandashifu/studio/images/aggregation.png
pandashifu/studio/images/anova.png
pandashifu/studio/images/bar_chart.png
pandashifu/studio/images/boolean_conditions.png
pandashifu/studio/images/box_plot.png
pandashifu/studio/images/clustering.png
pandashifu/studio/images/correlation.png
pandashifu/studio/images/date_time.png
pandashifu/studio/images/decomposition.png
pandashifu/studio/images/filled_areas.png
pandashifu/studio/images/group_by.png
pandashifu/studio/images/heat_map.png
pandashifu/studio/images/histogram.png
pandashifu/studio/images/kde.png
pandashifu/studio/images/line_plot.png
pandashifu/studio/images/over_sampling.png
pandashifu/studio/images/pair_plot.png
pandashifu/studio/images/pivot_table.png
pandashifu/studio/images/probability_plot.png
pandashifu/studio/images/radar_chart.png
pandashifu/studio/images/random_sampling.png
pandashifu/studio/images/regression_plot.png
pandashifu/studio/images/scatter_plot.png
pandashifu/studio/images/scikit_learn_models.png
pandashifu/studio/images/select_columns.png
pandashifu/studio/images/sort_rows.png
pandashifu/studio/images/statsmodels.png
pandashifu/studio/images/time_trend.png
pandashifu/studio/images/treat_missing_values.png
pandashifu/studio/images/value_counts.png
pandashifu/studio/images/value_counts_operations.png
pandashifu/studio/images/variance_inflation_factor.png
pandashifu/studio/www/clipboard.svg
pandashifu/studio/www/color_binding.js
pandashifu/studio/www/copy_handler.js
pandashifu/studio/www/question-circle-fill.svg
pandashifu-1.2.1.dist-info/METADATA
pandashifu-1.2.1.dist-info/WHEEL
pandashifu-1.2.1.dist-info/top_level.txt
pandashifu-1.2.1.dist-info/RECORD
