Metadata-Version: 2.4
Name: pandashifu
Version: 1.2.1
Summary: PandaShifu is a user interface for descriptive and predictive analytics.
Author: Peng Xiong
Author-email: Peng Xiong <xiongpengnus@gmail.com>
Project-URL: Homepage, https://github.com/XiongPengNUS/PandaShifu
Project-URL: Issues, https://github.com/XiongPengNUS/PandaShifu/issues
Classifier: Programming Language :: Python :: 3
Classifier: License :: OSI Approved :: MIT License
Classifier: Operating System :: OS Independent
Requires-Python: >=3.12
Requires-Dist: shiny>=1.5.0
Requires-Dist: pandas>=2.2.3
Requires-Dist: numpy>=2.0.2
Requires-Dist: scipy>=1.15.3
Requires-Dist: xlsxwriter>=3.2.0
Requires-Dist: matplotlib>=3.10.3
Requires-Dist: seaborn>=0.13.2
Requires-Dist: scikit-learn>=1.7.1
Requires-Dist: imbalanced-learn>=0.14.0
Requires-Dist: statsmodels>=0.14.5
